<?xml version="1.0" encoding="UTF-8"?>
<objects serializationModel="Studio.02.02.00">
	<object class="AudioFile" id="{8ca245c9-171f-4286-a048-523076594db8}">
		<property name="assetPath">
			<value>pasos/footsteps_player_wood_01.ogg</value>
		</property>
		<property name="frequencyInKHz">
			<value>48</value>
		</property>
		<property name="channelCount">
			<value>1</value>
		</property>
		<property name="length">
			<value>0.5013333333333333</value>
		</property>
		<relationship name="masterAssetFolder">
			<destination>{9657067a-2381-4ee2-8bb6-29e105b26f1f}</destination>
		</relationship>
	</object>
</objects>
